AUTHORS.rst
CONTRIBUTING.rst
HISTORY.rst
LICENSE
MANIFEST.in
README.rst
setup.cfg
setup.py
djangocms_usersettings2/__init__.py
djangocms_usersettings2/cms_toolbar.py
djangocms_usersettings2/models.py
djangocms_usersettings2.egg-info/PKG-INFO
djangocms_usersettings2.egg-info/SOURCES.txt
djangocms_usersettings2.egg-info/dependency_links.txt
djangocms_usersettings2.egg-info/not-zip-safe
djangocms_usersettings2.egg-info/requires.txt
djangocms_usersettings2.egg-info/top_level.txt