Metadata-Version: 1.1
Name: djangocms-usersettings2
Version: 0.1.0
Summary: This package integrates django-usersettings2 with django-cms>=3.0, This allows a site editor to add/modify all usersettings in the frontend editing mode of django CMS and provide your users with a streamlined editing experience.
Home-page: https://github.com/mishbahr/djangocms-usersettings2
Author: Mishbah Razzaque
Author-email: mishbahx@gmail.com
License: BSD
Keywords: djangocms-usersettings2,site settings,django-cms
Platform: UNKNOWN
Classifier: Development Status :: 3 - Alpha
Classifier: Framework :: Django
Classifier: Intended Audience :: Developers
Classifier: License :: OSI Approved :: BSD License
Classifier: Natural Language :: English
Classifier: Programming Language :: Python :: 2
Classifier: Programming Language :: Python :: 2.6
Classifier: Programming Language :: Python :: 2.7
Classifier: Programming Language :: Python :: 3
Classifier: Programming Language :: Python :: 3.3
Classifier: Programming Language :: Python :: 3.4
